copernicus_seasonal_forecast_tools-0.1.2.dist-info/licenses/LICENSE
seasonal_forecast_tools/__init__.py
seasonal_forecast_tools/core/__init__.py
seasonal_forecast_tools/core/heat_index.py
seasonal_forecast_tools/core/index_definitions.py
seasonal_forecast_tools/core/seasonal_forecast.py
seasonal_forecast_tools/core/seasonal_statistics.py
seasonal_forecast_tools/data/__init__.py
seasonal_forecast_tools/data/downloader.py
seasonal_forecast_tools/utils/__init__.py
seasonal_forecast_tools/utils/config.py
seasonal_forecast_tools/utils/coordinates_utils.py
seasonal_forecast_tools/utils/path_utils.py
seasonal_forecast_tools/utils/time_utils.py
copernicus_seasonal_forecast_tools-0.1.2.dist-info/METADATA
copernicus_seasonal_forecast_tools-0.1.2.dist-info/WHEEL
copernicus_seasonal_forecast_tools-0.1.2.dist-info/top_level.txt
copernicus_seasonal_forecast_tools-0.1.2.dist-info/RECORD
