Metadata-Version: 2.4
Name: copernicus-seasonal-forecast-tools
Version: 0.1.2
Summary: CLIMADA-compatible module for generating and analyzing seasonal forecast hazards from Copernicus data
Author: Dahyann Araya
License-Expression: GPL-3.0-or-later
Classifier: Programming Language :: Python :: 3
Classifier: Programming Language :: Python :: 3.10
Classifier: Programming Language :: Python :: 3.11
Classifier: Operating System :: OS Independent
Classifier: Intended Audience :: Science/Research
Classifier: Topic :: Scientific/Engineering :: Atmospheric Science
Classifier: Topic :: Scientific/Engineering :: Hydrology
Classifier: Topic :: Scientific/Engineering :: Information Analysis
Requires-Python: <3.12,>=3.10
License-File: LICENSE
Requires-Dist: xarray
Requires-Dist: cfgrib
Requires-Dist: cdsapi
Requires-Dist: numpy
Requires-Dist: pandas
Requires-Dist: matplotlib
Requires-Dist: netCDF4
Requires-Dist: shapely
Requires-Dist: geopandas
Requires-Dist: cartopy
Dynamic: license-file
